cocoindex_code_mcp_server-0.2.0.dist-info/METADATA
cocoindex_code_mcp_server-0.2.0.dist-info/WHEEL
cocoindex_code_mcp_server-0.2.0.dist-info/entry_points.txt
cocoindex_code_mcp_server-0.2.0.dist-info/licenses/LICENSE
cocoindex_code_mcp_server.libs/libgcc_s-39080030.so.1
cocoindex_code_mcp_server/__init__.py
cocoindex_code_mcp_server/_haskell_tree_sitter.abi3.so
cocoindex_code_mcp_server/arg_parser_old.py
cocoindex_code_mcp_server/ast_chunking.py
cocoindex_code_mcp_server/ast_visitor.py
cocoindex_code_mcp_server/backends/__init__.py
cocoindex_code_mcp_server/backends/postgres_backend.py
cocoindex_code_mcp_server/backends/qdrant_backend.py
cocoindex_code_mcp_server/cocoindex_config.py
cocoindex_code_mcp_server/db/__init__.py
cocoindex_code_mcp_server/db/pgvector/__init__.py
cocoindex_code_mcp_server/db/pgvector/hybrid_search.py
cocoindex_code_mcp_server/grammars/keyword_search.lark
cocoindex_code_mcp_server/keyword_search_parser_lark.py
cocoindex_code_mcp_server/lang/__init__.py
cocoindex_code_mcp_server/lang/haskell/__init__.py
cocoindex_code_mcp_server/lang/haskell/haskell_ast_chunker.py
cocoindex_code_mcp_server/lang/python/__init__.py
cocoindex_code_mcp_server/lang/python/python_code_analyzer.py
cocoindex_code_mcp_server/lang/python/tree_sitter_python_analyzer.py
cocoindex_code_mcp_server/language_handlers/__init__.py
cocoindex_code_mcp_server/language_handlers/c_visitor.py
cocoindex_code_mcp_server/language_handlers/cpp_visitor.py
cocoindex_code_mcp_server/language_handlers/haskell_handler.py
cocoindex_code_mcp_server/language_handlers/java_visitor.py
cocoindex_code_mcp_server/language_handlers/javascript_visitor.py
cocoindex_code_mcp_server/language_handlers/kotlin_visitor.py
cocoindex_code_mcp_server/language_handlers/python_handler.py
cocoindex_code_mcp_server/language_handlers/rust_visitor.py
cocoindex_code_mcp_server/language_handlers/typescript_visitor.py
cocoindex_code_mcp_server/main_hybrid_search.py
cocoindex_code_mcp_server/main_interactive_query.py
cocoindex_code_mcp_server/main_mcp_server.py
cocoindex_code_mcp_server/mappers.py
cocoindex_code_mcp_server/mcp_json_schemas.py
cocoindex_code_mcp_server/parser_util.py
cocoindex_code_mcp_server/py.typed
cocoindex_code_mcp_server-0.2.0.dist-info/RECORD
