Metadata-Version: 2.4
Name: cocoindex_code_mcp_server
Version: 0.2.0
Classifier: Programming Language :: Python :: 3
Classifier: Programming Language :: Python :: 3 :: Only
Classifier: Programming Language :: Python :: 3.11
Classifier: Programming Language :: Python :: 3.12
Classifier: Programming Language :: Python :: 3.13
Classifier: Programming Language :: Python :: 3.14
Classifier: Programming Language :: Rust
Classifier: Operating System :: OS Independent
Classifier: Development Status :: 4 - Beta
Classifier: Topic :: Software Development
Classifier: Topic :: Software Development :: Libraries :: Python Modules
Classifier: Topic :: Text Processing :: Linguistic
Classifier: Topic :: Text Processing :: Indexing
Classifier: Topic :: Scientific/Engineering :: Artificial Intelligence
Classifier: License :: OSI Approved :: GNU Affero General Public License v3 or later (AGPLv3+)
Classifier: Intended Audience :: Developers
Classifier: Intended Audience :: Information Technology
Classifier: Intended Audience :: Science/Research
Requires-Dist: cocoindex[embeddings]>=0.1.63
Requires-Dist: python-dotenv>=1.0.1
Requires-Dist: psycopg[pool]>=3.2.9
Requires-Dist: psycopg[binary]>=3.1.0
Requires-Dist: psycopg-pool>=3.1.0
Requires-Dist: pgvector>=0.4.1
Requires-Dist: numpy>=2.3.1
Requires-Dist: astchunk>=0.1.0
Requires-Dist: lark-parser>=0.12.0
Requires-Dist: prompt-toolkit>=3.0.0
Requires-Dist: cachetools>=6.1.0
Requires-Dist: click>=8.2.1
Requires-Dist: mcp>=1.12.0
Requires-Dist: tree-sitter>=0.23.0,<0.24.0
Requires-Dist: tree-sitter-python>=0.23.6,<0.24.0
Requires-Dist: tree-sitter-c-sharp>=0.23.1,<0.24.0
Requires-Dist: tree-sitter-java>=0.23.5,<0.24.0
Requires-Dist: tree-sitter-typescript>=0.23.2,<0.24.0
Requires-Dist: tree-sitter-c>=0.21.4,<0.23.0
Requires-Dist: tree-sitter-cpp>=0.22.3,<0.23.0
Requires-Dist: tree-sitter-rust>=0.21.2,<0.23.0
Requires-Dist: tree-sitter-kotlin>=1.0.0
Requires-Dist: tree-sitter-javascript>=0.23.1,<0.24.0
Requires-Dist: maturin>=1.9.6
Requires-Dist: typing-extensions>=4.15.0
Requires-Dist: pytest>=8.4.1 ; extra == 'test'
Requires-Dist: pytest-cov>=7.0.0 ; extra == 'test'
Requires-Dist: pytest-asyncio>=1.1.0 ; extra == 'test'
Requires-Dist: pytest-mock>=3.10.0 ; extra == 'test'
Requires-Dist: pytest-timeout>=2.1.0 ; extra == 'test'
Requires-Dist: pytest-xdist>=3.4.0 ; extra == 'test'
Requires-Dist: pytest-mypy>=1.0.1 ; extra == 'test'
Requires-Dist: coverage>=7.9.2 ; extra == 'test'
Requires-Dist: asyncpg>=0.29.0 ; extra == 'test'
Requires-Dist: cocoindex-code-mcp-server[test] ; extra == 'test'
Requires-Dist: maturin>=1.0,<2.0 ; extra == 'build'
Requires-Dist: mypy>=1.10.0 ; extra == 'build'
Requires-Dist: monkeytype>=23.3.0 ; extra == 'build'
Requires-Dist: pytest-monkeytype>=1.1.0 ; extra == 'build'
Requires-Dist: auto-type-annotate>=1.1.2 ; extra == 'build'
Requires-Dist: isort>=6.0.1 ; extra == 'build'
Requires-Dist: autoflake8>=0.4.1 ; extra == 'build'
Requires-Dist: autopep8>=2.0.0 ; extra == 'build'
Requires-Dist: flake8>=7.3.0 ; extra == 'build'
Requires-Dist: autopep8>=2.0.0 ; extra == 'build'
Requires-Dist: pipdeptree>=2.8.0 ; extra == 'build'
Requires-Dist: deptry>=0.14.0 ; extra == 'build'
Requires-Dist: pydocstyle>=6.3.0 ; extra == 'build'
Requires-Dist: ruff>=0.4.0 ; extra == 'build'
Requires-Dist: pylint>=4.0.2 ; extra == 'build'
Requires-Dist: cocoindex-code-mcp-server[build] ; extra == 'build'
Requires-Dist: pre-commit>=4.3.0 ; extra == 'build'
Requires-Dist: twine>=6.2.0 ; extra == 'act'
Requires-Dist: maturin[patchelf]>=1.0,<2.0 ; extra == 'act'
Requires-Dist: auditwheel>=6.2.0 ; extra == 'act'
Requires-Dist: abi3audit>=0.0.22 ; extra == 'act'
Requires-Dist: cibuildwheel>=3.2.1 ; extra == 'act'
Requires-Dist: delvewheel>=1.11.2 ; extra == 'act'
Requires-Dist: delocate>=0.8.1 ; extra == 'act'
Requires-Dist: cocoindex-code-mcp-server[act] ; extra == 'act'
Provides-Extra: test
Provides-Extra: build
Provides-Extra: act
License-File: LICENSE
Summary: RAG based on cocoindex as MCP server (streamingHttp), with Haskell support
Author-email: aanno <aanno@users.noreply.github.com>
Requires-Python: >=3.11
Project-URL: Homepage, https://github.com/aanno/cocoindex-code-mcp-server
Project-URL: Issues, https://github.com/aanno/cocoindex-code-mcp-server/issues
